rafter_cli/__main__.py
rafter_cli-0.1.0.dist-info/METADATA
rafter_cli-0.1.0.dist-info/WHEEL
rafter_cli-0.1.0.dist-info/entry_points.txt
rafter_cli-0.1.0.dist-info/RECORD
